python_colourlovers-0.1.1.dist-info/top_level.txt
python_colourlovers-0.1.1.dist-info/WHEEL
python_colourlovers-0.1.1.dist-info/RECORD
python_colourlovers-0.1.1.dist-info/DESCRIPTION.rst
python_colourlovers-0.1.1.dist-info/METADATA
python_colourlovers-0.1.1.dist-info/metadata.json
colourlovers/__init__.py
