Metadata-Version: 2.0
Name: python-colourlovers
Version: 0.1.1
Summary: An API providing access to the ColourLovers website.
Home-page: http://python-colourlovers.readthedocs.org
Author: Sebastian Vetter
Author-email: seb@roadsi.de
License: GNU General Public License (GPL)
Platform: UNKNOWN
Classifier: Development Status :: 4 - Beta
Classifier: Environment :: Console
Classifier: Environment :: Web Environment
Classifier: License :: OSI Approved :: GNU General Public License (GPL)
Classifier: Intended Audience :: Developers
Classifier: Natural Language :: English
Classifier: Operating System :: POSIX
Classifier: Operating System :: OS Independent
Classifier: Operating System :: MacOS :: MacOS X
Classifier: Operating System :: Microsoft :: Windows
Classifier: Programming Language :: Python
Classifier: Topic :: Software Development :: Libraries :: Python Modules
Provides: colourlovers
Requires-Dist: requests (>=1.0)
